{
    "startPage": "/local-authority-details",
    "pages": [
        {
            "path": "/check-your-answers",
            "title": "Check your answers",
            "components": [],
            "next": [],
            "section": "CdGjnO",
            "controller": "./pages/summary.js"
        },
        {
            "path": "/lead-contact-details",
            "title": "Lead contact details",
            "components": [
                {
                    "type": "Para",
                    "content": "The main point of contact for this application.",
                    "options": {},
                    "schema": {},
                    "name": "bxcVpP"
                },
                {
                    "options": {},
                    "type": "TextField",
                    "title": "Lead contact first name",
                    "hint": "",
                    "schema": {},
                    "name": "sdrrOT"
                },
                {
                    "options": {},
                    "type": "TextField",
                    "title": "Lead contact last name",
                    "hint": "",
                    "schema": {},
                    "name": "itKcJz"
                },
                {
                    "options": {},
                    "type": "TextField",
                    "title": "Lead contact job title",
                    "hint": "",
                    "schema": {},
                    "name": "gswBOa"
                },
                {
                    "options": {},
                    "type": "EmailAddressField",
                    "title": "Lead contact email address",
                    "hint": "",
                    "schema": {},
                    "name": "BkuACU"
                }
            ],
            "next": [
                {
                    "path": "/check-your-answers"
                }
            ],
            "section": "CdGjnO"
        },
        {
            "path": "/local-authority-details",
            "title": "Local authority details",
            "components": [
                {
                    "type": "Para",
                    "content": "<p class=\"govuk-body govuk-!-font-weight-bold\">In this section, we'll ask for:</p>\n<ul class=\"govuk-list govuk-list--bullet\">\n<li>your local authority name</li>\n<li>your lead contact's name</li>\n<li>your lead contact's job title</li>\n<li>your lead contact's email address</li>\n</ul>",
                    "options": {},
                    "schema": {},
                    "name": "nmKurP"
                }
            ],
            "next": [
                {
                    "path": "/local-authority-name"
                }
            ],
            "section": "CdGjnO",
            "controller": "start.js"
        },
        {
            "path": "/local-authority-name",
            "title": "Local authority name",
            "components": [
                {
                    "options": {},
                    "type": "AutocompleteField",
                    "title": "Local authority name",
                    "hint": "",
                    "schema": {},
                    "name": "RoLhhf",
                    "list": "vlTWym",
                    "values": {
                        "type": "listRef"
                    }
                }
            ],
            "next": [
                {
                    "path": "/lead-contact-details"
                }
            ],
            "section": "CdGjnO"
        }
    ],
    "lists": [
        {
            "type": "string",
            "items": [
                {
                    "text": "Cambridgeshire County Council",
                    "value": "Cambridgeshire County Council"
                },
                {
                    "text": "Derbyshire County Council",
                    "value": "Derbyshire County Council"
                },
                {
                    "text": "Devon County Council",
                    "value": "Devon County Council"
                },
                {
                    "text": "East Sussex County Council",
                    "value": "East Sussex County Council"
                },
                {
                    "text": "Essex County Council",
                    "value": "Essex County Council"
                },
                {
                    "text": "Gloucestershire County Council",
                    "value": "Gloucestershire County Council"
                },
                {
                    "text": "Hampshire County Council",
                    "value": "Hampshire County Council"
                },
                {
                    "text": "Hertfordshire County Council",
                    "value": "Hertfordshire County Council"
                },
                {
                    "text": "Kent County Council",
                    "value": "Kent County Council"
                },
                {
                    "text": "Lancashire County Council",
                    "value": "Lancashire County Council"
                },
                {
                    "text": "Leicestershire County Council",
                    "value": "Leicestershire County Council"
                }
            ],
            "name": "vlTWym",
            "title": "Local authorities"
        }
    ],
    "conditions": [],
    "sections": [
        {
            "name": "CdGjnO",
            "title": "Local authority details",
            "hideTitle": true
        }
    ],
    "outputs": [],
    "skipSummary": false,
    "name": "Apply for Local plans delivery fund"
}